{
  "$schema": "https://alps-io.github.io/schemas/alps.json",
  "alps": {
    "version": "1.0",
    "descriptor": [
      {
        "id": "highPrice",
        "def": "https://schema.org/highPrice",
        "name": "highPrice",
        "type": "semantic"
      },
      {
        "id": "highPriceNumber",
        "def": "https://schema.org/highPrice",
        "name": "highPrice",
        "type": "semantic"
      },
      {
        "id": "highPriceText",
        "def": "https://schema.org/highPrice",
        "name": "highPrice",
        "type": "semantic"
      }
    ]
  }
}