{
  "$schema": "https://alps-io.github.io/schemas/alps.json",
  "alps": {
    "version": "1.0",
    "descriptor": [
      {
        "id": "monthlyMinimumRepaymentAmount",
        "def": "https://schema.org/monthlyMinimumRepaymentAmount",
        "name": "monthlyMinimumRepaymentAmount",
        "type": "semantic"
      },
      {
        "id": "monthlyMinimumRepaymentAmountMonetaryAmount",
        "def": "https://schema.org/monthlyMinimumRepaymentAmount",
        "name": "monthlyMinimumRepaymentAmount",
        "type": "semantic"
      },
      {
        "id": "monthlyMinimumRepaymentAmountNumber",
        "def": "https://schema.org/monthlyMinimumRepaymentAmount",
        "name": "monthlyMinimumRepaymentAmount",
        "type": "semantic"
      }
    ]
  }
}