{
  "$schema": "https://alps-io.github.io/schemas/alps.json",
  "alps": {
    "version": "1.0",
    "descriptor": [
      {
        "id": "QuantitativeValueDistribution",
        "def": "https://schema.org/QuantitativeValueDistribution",
        "descriptor": [
          {
            "href": "./additionalType.json#additionalType"
          },
          {
            "href": "./alternateName.json#alternateName"
          },
          {
            "href": "./description.json#description"
          },
          {
            "href": "./disambiguatingDescription.json#disambiguatingDescription"
          },
          {
            "href": "./duration.json#duration"
          },
          {
            "href": "./identifier.json#identifier"
          },
          {
            "href": "./image.json#image"
          },
          {
            "href": "./mainEntityOfPage.json#mainEntityOfPage"
          },
          {
            "href": "./median.json#median"
          },
          {
            "href": "./name.json#name"
          },
          {
            "href": "./percentile10.json#percentile10"
          },
          {
            "href": "./percentile25.json#percentile25"
          },
          {
            "href": "./percentile75.json#percentile75"
          },
          {
            "href": "./percentile90.json#percentile90"
          },
          {
            "href": "./potentialAction.json#potentialAction"
          },
          {
            "href": "./sameAs.json#sameAs"
          },
          {
            "href": "./subjectOf.json#subjectOf"
          },
          {
            "href": "./url.json#url"
          }
        ]
      }
    ]
  }
}