{
  "$schema": "https://alps-io.github.io/schemas/alps.json",
  "alps": {
    "version": "1.0",
    "descriptor": [
      {
        "id": "pageStart",
        "def": "https://schema.org/pageStart",
        "name": "pageStart",
        "type": "semantic"
      },
      {
        "id": "pageStartInteger",
        "def": "https://schema.org/pageStart",
        "name": "pageStart",
        "type": "semantic"
      },
      {
        "id": "pageStartText",
        "def": "https://schema.org/pageStart",
        "name": "pageStart",
        "type": "semantic"
      }
    ]
  }
}